paynow/__init__.py
paynow/__main__.py
paynow/model.py
achironet_paynow-1.0.0.dist-info/LICENSE.txt
achironet_paynow-1.0.0.dist-info/METADATA
achironet_paynow-1.0.0.dist-info/WHEEL
achironet_paynow-1.0.0.dist-info/top_level.txt
achironet_paynow-1.0.0.dist-info/RECORD
