Metadata-Version: 2.1
Name: achironet-paynow
Version: 1.0.0
Summary: Paynow Python SDK
Home-page: https://github.com/ifelsegrandmaster/Paynow-Python-SDK
Author: WebDev Projects
Author-email: pkg-dev@webdevworld.com
License: UNKNOWN
Project-URL: Bug Reports, https://github.com/ifelsegrandmaster/Paynow-Python-SDK/issues
Project-URL: Source, https://github.com/ifelsegrandmaster/Paynow-Python-SDK
Keywords: achironet paynow-api -paynow-zimbabwe paynow-zimbabwe-api paynow-zimbabwe-sdk
Platform: UNKNOWN
Classifier: Development Status :: 5 - Production/Stable
Classifier: License :: OSI Approved :: MIT License
Classifier: Programming Language :: Python :: 2
Classifier: Programming Language :: Python :: 2.7
Classifier: Programming Language :: Python :: 3
Classifier: Programming Language :: Python :: 3.4
Classifier: Programming Language :: Python :: 3.5
Classifier: Programming Language :: Python :: 3.6
License-File: LICENSE.txt
Requires-Dist: requests
